gai/ttt/__init__.py
gai/ttt/client/__init__.py
gai/ttt/client/completions.py
gai/ttt/client/requirements.txt
gai_ttt-0.1887.dist-info/LICENSE
gai_ttt-0.1887.dist-info/METADATA
gai_ttt-0.1887.dist-info/WHEEL
gai_ttt-0.1887.dist-info/RECORD
